openue/__init__.py
openue/data/__init__.py
openue/data/base_data_module.py
openue/data/data_module.py
openue/data/processor.py
openue/data/utils.py
openue/lit_models/__init__.py
openue/lit_models/base.py
openue/lit_models/metric.py
openue/lit_models/transformer.py
openue/models/__init__.py
openue/models/model.py
openue-0.2.5.dist-info/LICENSE
openue-0.2.5.dist-info/METADATA
openue-0.2.5.dist-info/WHEEL
openue-0.2.5.dist-info/top_level.txt
openue-0.2.5.dist-info/RECORD
