Metadata-Version: 2.1
Name: openue
Version: 0.2.5
Summary: An open toolkit of universal extraction from text.
Home-page: https://github.com/zjunlp/openue
Author: zxlzr
Author-email: jack16900@gmail.com
License: UNKNOWN
Platform: UNKNOWN
Classifier: Programming Language :: Python :: 3
Classifier: License :: OSI Approved :: MIT License
Classifier: Operating System :: OS Independent
Requires-Python: >=3.6
License-File: LICENSE
Requires-Dist: jsonlines (>=2.0.0)
Requires-Dist: tqdm (>=4.49.0)
Requires-Dist: wandb (>=0.10.30)
Requires-Dist: packaging (>=20.9)
Requires-Dist: numpy (>=1.19.5)
Requires-Dist: tensorboard (>=2.4.1)
Requires-Dist: pytorch-lightning (==1.3.1)
Requires-Dist: transformers (>=4.7.0)
Requires-Dist: dataclasses (>=0.6)
Requires-Dist: PyYAML (==5.4.1)
Requires-Dist: tensorboardX (>=2.2)
Requires-Dist: textbrewer (>=0.2.1)
Requires-Dist: ts (>=0.5.1)
